pyreports/__init__.py
pyreports/cli.py
pyreports/core.py
pyreports/datatools.py
pyreports/exception.py
pyreports/io.py
pyreports-1.8.1.dist-info/licenses/LICENSE.md
pyreports-1.8.1.dist-info/METADATA
pyreports-1.8.1.dist-info/WHEEL
pyreports-1.8.1.dist-info/entry_points.txt
pyreports-1.8.1.dist-info/top_level.txt
pyreports-1.8.1.dist-info/RECORD
