Metadata-Version: 2.4
Name: pyreports
Version: 1.8.1
Summary: pyreports is a python library that allows you to create complex report from various sources.
Home-page: https://github.com/MatteoGuadrini/pyreports
Author: Matteo Guadrini
Author-email: Matteo Guadrini <matteo.guadrini@hotmail.it>
Maintainer: Matteo Guadrini
Maintainer-email: Matteo Guadrini <matteo.guadrini@hotmail.it>
License: GNU General Public License v3.0
Project-URL: homepage, https://github.com/MatteoGuadrini/pyreports
Project-URL: documentation, https://pyreports.readthedocs.io/en/latest/
Project-URL: repository, https://github.com/MatteoGuadrini/pyreports.git
Project-URL: changelog, https://github.com/MatteoGuadrini/pyreports/blob/master/CHANGES.md
Keywords: pyreports,reports,report,csv,yaml,export,excel,database,ldap,dataset,file,executor,book
Classifier: Programming Language :: Python :: 3
Classifier: License :: OSI Approved :: GNU General Public License v3 (GPLv3)
Classifier: Operating System :: OS Independent
Requires-Python: >=3.8
License-File: LICENSE.md
Requires-Dist: ldap3
Requires-Dist: mysql-connector-python
Requires-Dist: psycopg2-binary
Requires-Dist: tablib
Requires-Dist: tablib[all]
Requires-Dist: nosqlapi
Requires-Dist: pyyaml
Dynamic: author
Dynamic: home-page
Dynamic: license-file
Dynamic: maintainer
Dynamic: requires-python
